<?xml version = '1.0' encoding = 'UTF-8'?>
<Relation class="oracle.dbtools.crest.model.design.logical.Relation" name="Relation_98" directorySegmentName="seg_0" id="30EE178D-F227-B1B6-D05A-8EAE5A212F3B">
<createdBy>BBM</createdBy>
<createdTime>2021-01-23 18:18:38 UTC</createdTime>
<ownerDesignName>BBM_ASPACE</ownerDesignName>
<engineerTo>
<item key="22FBB7C8-E61E-D7C0-C388-B9FA35C9CE32" value="true"/>
</engineerTo>
<identifying>false</identifying>
<optionalSource>true</optionalSource>
<optionalTarget>false</optionalTarget>
<sourceCardinality>1</sourceCardinality>
<sourceEntity>C76E9559-7036-F20F-50C8-3BB2747200BA</sourceEntity>
<targetCardinalityString>*</targetCardinalityString>
<targetEntity>F6ECAA99-53FF-D3BA-0CDB-D3630C2511E5</targetEntity>
<transferable>true</transferable>
<deleteRule>NO ACTION</deleteRule>
</Relation>